odoo8_addon_membership_prorrate-8.0.1.0.0.99.dev18-py3.8-nspkg.pth
odoo_addons/membership_prorrate/README.rst
odoo_addons/membership_prorrate/__init__.py
odoo_addons/membership_prorrate/__openerp__.py
odoo_addons/membership_prorrate/i18n/ca.po
odoo_addons/membership_prorrate/i18n/de.po
odoo_addons/membership_prorrate/i18n/es.po
odoo_addons/membership_prorrate/i18n/es_MX.po
odoo_addons/membership_prorrate/i18n/fi.po
odoo_addons/membership_prorrate/i18n/fr.po
odoo_addons/membership_prorrate/i18n/fr_CH.po
odoo_addons/membership_prorrate/i18n/hr.po
odoo_addons/membership_prorrate/i18n/hr_HR.po
odoo_addons/membership_prorrate/i18n/it.po
odoo_addons/membership_prorrate/i18n/membership_prorrate.pot
odoo_addons/membership_prorrate/i18n/nl_NL.po
odoo_addons/membership_prorrate/i18n/pt_BR.po
odoo_addons/membership_prorrate/i18n/pt_PT.po
odoo_addons/membership_prorrate/i18n/ro.po
odoo_addons/membership_prorrate/i18n/sl.po
odoo_addons/membership_prorrate/i18n/tr.po
odoo_addons/membership_prorrate/i18n/tr_TR.po
odoo_addons/membership_prorrate/i18n/vi_VN.po
odoo_addons/membership_prorrate/i18n/zh_CN.po
odoo_addons/membership_prorrate/models/__init__.py
odoo_addons/membership_prorrate/models/account_invoice.py
odoo_addons/membership_prorrate/models/product_template.py
odoo_addons/membership_prorrate/static/description/icon.png
odoo_addons/membership_prorrate/static/description/icon.svg
odoo_addons/membership_prorrate/tests/__init__.py
odoo_addons/membership_prorrate/tests/test_membership_prorrate.py
odoo_addons/membership_prorrate/views/product_template_views.xml
odoo8_addon_membership_prorrate-8.0.1.0.0.99.dev18.dist-info/METADATA
odoo8_addon_membership_prorrate-8.0.1.0.0.99.dev18.dist-info/WHEEL
odoo8_addon_membership_prorrate-8.0.1.0.0.99.dev18.dist-info/namespace_packages.txt
odoo8_addon_membership_prorrate-8.0.1.0.0.99.dev18.dist-info/top_level.txt
odoo8_addon_membership_prorrate-8.0.1.0.0.99.dev18.dist-info/RECORD
